json5/__init__.py
json5/__main__.py
json5/arg_parser.py
json5/host.py
json5/lib.py
json5/parser.py
json5/py.typed
json5/tool.py
json5/version.py
json5-0.9.28.dist-info/LICENSE
json5-0.9.28.dist-info/METADATA
json5-0.9.28.dist-info/WHEEL
json5-0.9.28.dist-info/entry_points.txt
json5-0.9.28.dist-info/top_level.txt
json5-0.9.28.dist-info/RECORD
